[
  {
    "name": "- 1 A - Classic Rock von 1A Radio",
    "uri": "https://1a-classicrock.radionetz.de/1a-classicrock.mp3",
    "added": 1761511059
  },
  {
    "name": "Chillofi radio",
    "uri": "https://azc.rdstream-5677.dez.ovh/listen/chillofi/radio.mp3",
    "added": 1761446827
  },
  {
    "name": "1LIVE Chillout",
    "uri": "https://f131.rndfnk.com/ard/wdr/1live/chillout/mp3/128/stream.mp3?cid=01GRBW9YMFF3AKBC3JQ513E69J&sid=34ZmKUashgSv1Utlk9fl7O3dXvy&token=glGejNBohFOuuzWRq1s1UszAHZkqS6B8ntddF7RvVek&tvf=6yk2LFvucRhmMTMxLnJuZGZuay5jb20",
    "added": 1761444332
  },
  {
    "name": " Radio ZET Chilli ",
    "uri": "https://ch04.cdn.eurozet.pl/chi-net.mp3?redirected=04",
    "added": 1761444231
  },
  {
    "name": "- 0 N - Chillout on Radio",
    "uri": "https://0n-chillout.radionetz.de/0n-chillout.mp3",
    "added": 1761444173
  },
  {
    "name": "- 1 A - Chillout von 1A Radio",
    "uri": "https://1a-chillout.radionetz.de/1a-chillout.mp3",
    "added": 1761444147
  },
  {
    "name": "181.FM - Chilled Out",
    "uri": "http://listen.181fm.com/181-chilled_128k.mp3",
    "added": 1761444062
  },
  {
    "name": "ABradio Chillout",
    "uri": "http://mp3stream4.abradio.cz/chillout128.mp3",
    "added": 1761443947
  }
]